README.rst
setup.cfg
setup.py
brasil/__init__.py
brasil.vocab.egg-info/PKG-INFO
brasil.vocab.egg-info/SOURCES.txt
brasil.vocab.egg-info/dependency_links.txt
brasil.vocab.egg-info/entry_points.txt
brasil.vocab.egg-info/namespace_packages.txt
brasil.vocab.egg-info/not-zip-safe
brasil.vocab.egg-info/requires.txt
brasil.vocab.egg-info/top_level.txt
brasil/vocab/__init__.py
brasil/vocab/geo/__init__.py
brasil/vocab/geo/cidade.py
brasil/vocab/geo/pais.py
brasil/vocab/geo/uf.py
brasil/vocab/telecom/__init__.py
brasil/vocab/telecom/cng.py
brasil/vocab/telecom/ddd.py
brasil/vocab/tests/__init__.py
brasil/vocab/tests/test_geo.py
brasil/vocab/tests/test_telecom.py
docs/HISTORY.txt