Metadata-Version: 1.0
Name: brasil.vocab
Version: 0.8
Summary: Basic Brazilian vocabularies for Python
Home-page: https://github.com/simplesconsultoria/brasil.vocab
Author: Simples Consultoria
Author-email: products@simplesconsultoria.com.br
License: GPL
Keywords: brasil vocabularies vocabularios brazil
Platform: UNKNOWN
Classifier: Intended Audience :: Developers
Classifier: Intended Audience :: Telecommunications Industry
Classifier: Natural Language :: Portuguese (Brazilian)
Classifier: Programming Language :: Python
Classifier: Programming Language :: Python :: 2.4
Classifier: Programming Language :: Python :: 2.5
Classifier: Programming Language :: Python :: 2.6
Classifier: Programming Language :: Python :: 2.7
